TrainingAnimation/__init__.py
TrainingAnimation/anim.py
TrainingAnimation-0.0.12.dist-info/LICENSE
TrainingAnimation-0.0.12.dist-info/METADATA
TrainingAnimation-0.0.12.dist-info/WHEEL
TrainingAnimation-0.0.12.dist-info/top_level.txt
TrainingAnimation-0.0.12.dist-info/RECORD
