Metadata-Version: 2.1
Name: TrainingAnimation
Version: 0.0.12
Summary: Training AI model progress bar
Author: MaciejM
Requires-Python: >=3.6
License-File: LICENSE
Requires-Dist: numpy >=1.26.3
